med/__init__.py
med/room/processors/__init__.py
med/room/processors/class_principal.py
med/room/processors/data_views.py
med/room/processors/models.py
med/room/processors/transform_data.py
med/room/utils/__init__.py
med/room/utils/colorize.py
med/room/utils/custom_requests.py
med/room/utils/logger.py
med/room/utils/validate_key.py
MedRoom.AI.Test-0.0.8.dist-info/LICENSE
MedRoom.AI.Test-0.0.8.dist-info/METADATA
MedRoom.AI.Test-0.0.8.dist-info/WHEEL
MedRoom.AI.Test-0.0.8.dist-info/top_level.txt
MedRoom.AI.Test-0.0.8.dist-info/RECORD
